<?xml version='1.0' encoding='UTF-8'?>
<data>
  <interval begin="0" end="3600">
    <edge id="a210" entered="245" />
    <edge id="a117" entered="95" />
    <edge id="a43[0]" entered="148" />
    <edge id="b2[1][1][1]b" entered="1463" />
    <edge id="b31" entered="44" />
    <edge id="b53" entered="546" />
    <edge id="b53" entered="408" />
    <edge id="b15" entered="100" />
    <edge id="a55" entered="71" />
    <edge id="a210" entered="966" />
    <edge id="a77[1][1]" entered="476" />
    <edge id="a78[0]" entered="104" />
    <edge id="a134" entered="271" />
    <edge id="b2[1][1][1]b" entered="701" />
    <edge id="b2[1][0]" entered="1528" />
    <edge id="b23" entered="79" />
    <edge id="b38[0]" entered="262" />
    <edge id="b26.-170" entered="115" />
    <edge id="b76" entered="712" />
    <edge id="a204[1][1]" entered="661" />
    <edge id="a122" entered="1254" />
    <edge id="b17[1]" entered="266" />
    <edge id="b37" entered="123" />
    <edge id="a60" entered="127" />
    <edge id="a153" entered="82" />
    <edge id="a190" entered="531" />
    <edge id="b38[0]" entered="159" />
    <edge id="b4[1][1][1]" entered="768" />
    <edge id="b4[1][1][0]" entered="697" />
    <edge id="b71" entered="23" />
    <edge id="b55" entered="243" />
    <edge id="a78[0]" entered="118" />
    <edge id="a60" entered="766" />
    <edge id="a191" entered="57" />
    <edge id="a43[1]" entered="1121" />
    <edge id="a201" entered="756" />
    <edge id="b47" entered="342" />
    <edge id="b38[0]a" entered="160" />
    <edge id="b2[0]" entered="417" />
    <edge id="b2[1][0]" entered="998" />
    <edge id="a201" entered="1024" />
    <edge id="a204a[0]" entered="1603" />
    <edge id="b3[1]" entered="1495" />
    <edge id="b10" entered="195" />
    <edge id="b4[1][1][0]" entered="610" />
    <edge id="b53" entered="258" />
    <edge id="b12" entered="546" />
    <edge id="b12" entered="766" />
    <edge id="a204[1][1]" entered="480" />
    <edge id="a203[0]" entered="768" />
    <edge id="a201" entered="140" />
    <edge id="b20+19a" entered="55" />
    <edge id="a11" entered="376" />
    <edge id="a181" entered="296" />
    <edge id="b70" entered="70" />
    <edge id="a104" entered="144" />
    <edge id="a210" entered="1064" />
    <edge id="a20001+87[1][0]" entered="546" />
    <edge id="a67" entered="456" />
    <edge id="b2[1][0]" entered="484" />
    <edge id="a71" entered="1099" />
    <edge id="b38[1][0]" entered="103" />
    <edge id="b4[1][1][1]" entered="957" />
    <edge id="b8" entered="40" />
    <edge id="b55" entered="252" />
    <edge id="a55" entered="381" />
    <edge id="a124" entered="462" />
    <edge id="b17[1]" entered="107" />
    <edge id="a195" entered="600" />
    <edge id="a195" entered="89" />
  </interval>
</data>